HypeM.py
setup.cfg
setup.py
HypeM.py.egg-info/PKG-INFO
HypeM.py.egg-info/SOURCES.txt
HypeM.py.egg-info/dependency_links.txt
HypeM.py.egg-info/requires.txt
HypeM.py.egg-info/top_level.txt
test/test_HypeM.py