Metadata-Version: 1.1
Name: HypeM.py
Version: 1.1.0
Summary: Python 3 wrapper for the official HypeMachine API
Home-page: https://github.com/jameswenzel/HypeM.py
Author: James Wenzel
Author-email: wenzel.james.r@gmail.com
License: Apache License 2.0
Download-URL: http://github.com/jameswenzel/HypeM.py/tarball1.1.0
Keywords: hypem,music,hype,machine,blogs,api,blog
Platform: UNKNOWN
